avirtech_autoexport_jp2/__init__.py
avirtech_autoexport_jp2/avirtech_autoexport_jp2.py
avirtech_autoexport_jp2-0.0.3.dist-info/METADATA
avirtech_autoexport_jp2-0.0.3.dist-info/WHEEL
avirtech_autoexport_jp2-0.0.3.dist-info/top_level.txt
avirtech_autoexport_jp2-0.0.3.dist-info/RECORD
