Metadata-Version: 2.1
Name: avirtech-autoexport-jp2
Version: 0.0.3
Summary: Avirtech Python Library to Export TIF file which has GSD One to .JP2000 format in ArcGIS
Home-page: https://github.com/dwieka21-bit
Author: Dwieka
Author-email: patriadwieka@gmail.com
License: MIT
Platform: UNKNOWN
Classifier: Intended Audience :: Developers
Classifier: License :: OSI Approved :: MIT License
Classifier: Programming Language :: Python
Classifier: Programming Language :: Python :: 3
Classifier: Programming Language :: Python :: 3.6
Classifier: Programming Language :: Python :: 3.7
Classifier: Programming Language :: Python :: 3.8
Classifier: Programming Language :: Python :: 3.9
Classifier: Operating System :: OS Independent
Requires-Dist: numpy
